graphspy/__init__.py
graphspy/__main__.py
graphspy/cli.py
graphspy/static/css/style.css
graphspy/static/js/functions.js
graphspy/static/js/purify.min.js
graphspy/static/js/theme.js
graphspy/templates/OneDrive.html
graphspy/templates/SharePoint.html
graphspy/templates/SharePointDrives.html
graphspy/templates/SharePointSites.html
graphspy/templates/access_token_modal.html
graphspy/templates/access_tokens.html
graphspy/templates/custom_requests.html
graphspy/templates/device_certificates.html
graphspy/templates/device_codes.html
graphspy/templates/entra_users.html
graphspy/templates/generic_search.html
graphspy/templates/index.html
graphspy/templates/layout.html
graphspy/templates/mfa.html
graphspy/templates/outlook.html
graphspy/templates/outlook_graph.html
graphspy/templates/primary_refresh_tokens.html
graphspy/templates/recent_files.html
graphspy/templates/refresh_token_modal.html
graphspy/templates/refresh_tokens.html
graphspy/templates/settings.html
graphspy/templates/shared_with_me.html
graphspy/templates/teams.html
graphspy/templates/winhello_keys.html
graphspy-1.6.1.dist-info/WHEEL
graphspy-1.6.1.dist-info/entry_points.txt
graphspy-1.6.1.dist-info/METADATA
graphspy-1.6.1.dist-info/RECORD
