Metadata-Version: 2.3
Name: graphspy
Version: 1.6.1
Summary: Initial Access and Post-Exploitation Tool for AAD and O365 with a browser-based GUI.
Author: RedByte1337
License: BSD-3-Clause
Requires-Dist: flask>=3.0.0,<4.0.0
Requires-Dist: pyjwt>=2.8.0,<3.0.0
Requires-Dist: requests>=2.30.0,<3.0.0
Requires-Dist: pyotp>=2.9.0,<3.0.0
Requires-Dist: fido2>=1.1.0,<3.0.0
Requires-Python: >=3.10, <4.0
Project-URL: repository, https://github.com/RedByte1337/GraphSpy
